VertexEngine/SimpleGUI.py
VertexEngine/VertexScreenModifiers.py
VertexEngine/__init__.py
VertexEngine/assets.py
VertexEngine/audio.py
VertexEngine/engine.py
VertexEngine/example.py
VertexEngine/scenes.py
VertexEngine/AdvancedVWidgets/ChatBubble.py
VertexEngine/AdvancedVWidgets/ChekBox.py
VertexEngine/AdvancedVWidgets/Counter.py
VertexEngine/AdvancedVWidgets/Dropdown.py
VertexEngine/AdvancedVWidgets/List.py
VertexEngine/AdvancedVWidgets/StatusLight.py
VertexEngine/AdvancedVWidgets/ToggleSwitch.py
VertexEngine/AdvancedVWidgets/WindowMods.py
VertexEngine/AdvancedVWidgets/Windows.py
VertexEngine/InputSystem/BtnInputs.py
VertexEngine/InputSystem/Events.py
VertexEngine/InputSystem/KeyInputs.py
VertexEngine/Vertex/__init__.py
VertexEngine/examples/test.py
VertexEngine/examples/games/Dodge/main.py
VertexEngine/examples/games/platformer/main.py
VertexEngine/examples/games/snake/main.py
vertexengine-1.2.2.dist-info/licenses/LICENSE
vertexengine-1.2.2.dist-info/METADATA
vertexengine-1.2.2.dist-info/WHEEL
vertexengine-1.2.2.dist-info/top_level.txt
vertexengine-1.2.2.dist-info/RECORD
