Metadata-Version: 2.4
Name: VertexEngine
Version: 1.2.2
Summary: An SDK for Python Development.
Author-email: Tyrel Miguel <annbasilan0828@gmail.com>
License: MIT
Project-URL: Documentation, https://vertexenginedocs.netlify.app/
Project-URL: Source, https://github.com/TyrelGomez/VertexEngine-Code
Project-URL: Issues, https://github.com/TyrelGomez/VertexEngine-Code/issues
Requires-Python: >=3.10
License-File: LICENSE
Requires-Dist: pygame>=2.0
Requires-Dist: PyQt6>=6.7
Dynamic: license-file
